README.rst
setup.py
Config_gen.egg-info/PKG-INFO
Config_gen.egg-info/SOURCES.txt
Config_gen.egg-info/dependency_links.txt
Config_gen.egg-info/entry_points.txt
Config_gen.egg-info/requires.txt
Config_gen.egg-info/top_level.txt
config_gen/__init__.py
config_gen/__main__.py
config_gen/exceptions.py
config_gen/utils.py
config_gen/commands/__init__.py
config_gen/commands/quickstart.py
config_gen/commands/render.py
config_gen/commands/render_file.py
config_gen/readers/__init__.py
config_gen/readers/read_csv.py
config_gen/readers/read_ini.py
config_gen/readers/read_json.py
config_gen/readers/read_py.py
config_gen/readers/read_txt.py