Metadata-Version: 1.1
Name: Config-gen
Version: 1.0-alpha6
Summary: Utility to generate configuration files
Home-page: https://github.com/rshk/config-gen
Author: Samuele Santi
Author-email: samuele@samuelesanti.com
License: GNU General Public License v3 or later (GPLv3+)
Platform: UNKNOWN
Classifier: Environment :: Console
Classifier: License :: OSI Approved :: GNU General Public License v3 or later (GPLv3+)
Classifier: Topic :: Utilities
